repo_links/__init__.py
repo_links/ci.py
repo_links/cli.py
repo_links/code.py
repo_links/git.py
repo_links/typing.py
repo_links-0.1.0.dist-info/METADATA
repo_links-0.1.0.dist-info/WHEEL
repo_links-0.1.0.dist-info/entry_points.txt
repo_links-0.1.0.dist-info/top_level.txt
repo_links-0.1.0.dist-info/RECORD
