Metadata-Version: 2.1
Name: repo-links
Version: 0.1.0
Summary: Quickly open URLs related to your repos
Home-page: https://github.com/seem/repo-links
Author: Wasim Lorgat
License: UNKNOWN
Platform: UNKNOWN
Requires-Dist: click
Requires-Dist: click-default-group
Provides-Extra: test
Requires-Dist: pytest ; extra == 'test'
